{"urls": [{"url": "https://hotelprinceseoul.co.kr/57/?q=YToxOntzOjEyOiJrZXl3b3JkX3R5cGUiO3M6MzoiYWxsIjt9&board=b2021082709c9059800d62&bmode=write&back_url=LzU3Lw%3D%3D", "id": "", "pw": ""}, {"url": "https://xn--bj0bpd29pnoff7f6zh4vi.com/52/?q=YToxOntzOjEyOiJrZXl3b3JkX3R5cGUiO3M6MzoiYWxsIjt9&board=b201811125be928fdf194d&bmode=write&back_url=LzUy", "id": "", "pw": ""}, {"url": "https://daic.co.kr/qna/?q=YToxOntzOjEyOiJrZXl3b3JkX3R5cGUiO3M6MzoiYWxsIjt9&board=b202207207bf4644d8c1d8&bmode=write&back_url=L3FuYS8%3D", "id": "", "pw": ""}, {"url": "https://www.netgang.kr/32/?q=YToxOntzOjEyOiJrZXl3b3JkX3R5cGUiO3M6MzoiYWxsIjt9&board=b20200214f4e92dfa0d0a3&bmode=write&back_url=LzMy", "id": "", "pw": ""}]}